multisqlite3manager/__init__.py
multisqlite3manager/file_manager/__init__.py
multisqlite3manager/file_manager/file_manager.py
multisqlite3manager/sqlite3_manager/__init__.py
multisqlite3manager/sqlite3_manager/sqlite3_manager.py
multisqlite3manager/sqlite3_manager/sqlite3_manager_test.py
milho_multi_sqlite3_manager-0.4.0.dist-info/METADATA
milho_multi_sqlite3_manager-0.4.0.dist-info/WHEEL
milho_multi_sqlite3_manager-0.4.0.dist-info/RECORD
