Metadata-Version: 2.1
Name: milho-multi-sqlite3-manager
Version: 0.4.0
Summary: 
Author: Guilherme S. Magalhães
Author-email: 40049979+Guisilcol@users.noreply.github.com
Requires-Python: >=3.7,<4.0
Classifier: Programming Language :: Python :: 3
Classifier: Programming Language :: Python :: 3.7
Classifier: Programming Language :: Python :: 3.8
Classifier: Programming Language :: Python :: 3.9
Classifier: Programming Language :: Python :: 3.10
Classifier: Programming Language :: Python :: 3.11
Requires-Dist: pandas (>=2.0.2,<3.0.0)
Requires-Dist: sqlalchemy (>=2.0.16,<3.0.0)
Requires-Dist: sqlglot (>=16.3.1,<17.0.0)
